docs/.gitignore
docs/Makefile
docs/conf.py
docs/index.rst
docs/models.rst
docs/notebooks.rst
docs/readme.md
docs/requirements.txt
docs/sample_collection.rst
docs/statistics.rst
docs/taxonomy.rst
docs/visualization.rst
docs/_static/one_codex_logo.png
docs/notebook_examples/notebooks_demo.ipynb
notebook_examples/example.ipynb
notebook_examples/notebooks_demo.ipynb
onecodex/__init__.py
onecodex/analyses.py
onecodex/api.py
onecodex/auth.py
onecodex/cli.py
onecodex/dataframes.py
onecodex/distance.py
onecodex/exceptions.py
onecodex/input_helpers.py
onecodex/metadata_upload.py
onecodex/stats.py
onecodex/taxonomy.py
onecodex/utils.py
onecodex/version.py
onecodex/assets/notebook_template.css
onecodex/assets/notebook_template.scss
onecodex/assets/notebook_template.tpl
onecodex/assets/one_codex_logo.png
onecodex/assets/fonts/FiraSans-Light.otf
onecodex/assets/fonts/FiraSans-Light.woff2
onecodex/assets/fonts/FiraSans-LightItalic.otf
onecodex/assets/fonts/FiraSans-LightItalic.woff2
onecodex/assets/fonts/FiraSans-Medium.otf
onecodex/assets/fonts/FiraSans-Medium.woff2
onecodex/assets/fonts/FiraSans-MediumItalic.otf
onecodex/assets/fonts/FiraSans-MediumItalic.woff2
onecodex/assets/fonts/FiraSans-Regular.otf
onecodex/assets/fonts/FiraSans-Regular.woff2
onecodex/assets/fonts/FiraSans-RegularItalic.otf
onecodex/assets/fonts/FiraSans-RegularItalic.woff2
onecodex/assets/fonts/FiraSans-SemiBold.otf
onecodex/assets/fonts/FiraSans-SemiBold.woff2
onecodex/assets/fonts/FiraSans-SemiBoldItalic.otf
onecodex/assets/fonts/FiraSans-SemiBoldItalic.woff2
onecodex/assets/fonts/FiraSansCondensed-Regular.otf
onecodex/assets/fonts/FiraSansCondensed-RegularItalic.otf
onecodex/assets/fonts/FiraSansCondensed-SemiBold.otf
onecodex/assets/fonts/FiraSansCondensed-SemiboldItalic.otf
onecodex/lib/__init__.py
onecodex/lib/auth.py
onecodex/lib/download.py
onecodex/lib/enums.py
onecodex/lib/files.py
onecodex/lib/helpers.py
onecodex/lib/upload.py
onecodex/models/__init__.py
onecodex/models/analysis.py
onecodex-0.19.4.dist-info/licenses/LICENSE
onecodex-0.19.4.dist-info/METADATA
onecodex-0.19.4.dist-info/WHEEL
onecodex-0.19.4.dist-info/entry_points.txt
onecodex-0.19.4.dist-info/top_level.txt
onecodex-0.19.4.dist-info/RECORD
