Metadata-Version: 2.4
Name: onecodex
Version: 0.19.4
Summary: One Codex API client and Python library
Author-email: One Codex <opensource@onecodex.com>
License: MIT License
Project-URL: Homepage, https://github.com/onecodex/onecodex
Project-URL: Repository, https://github.com/onecodex/onecodex
Keywords: One Codex API Client
Classifier: Environment :: Console
Classifier: License :: OSI Approved :: MIT License
Classifier: Topic :: Scientific/Engineering :: Bio-Informatics
Classifier: Topic :: Software Development :: Libraries :: Python Modules
Classifier: Topic :: Internet :: WWW/HTTP
Classifier: Programming Language :: Python :: 3
Classifier: Programming Language :: Python :: 3 :: Only
Classifier: Programming Language :: Python :: 3.10
Classifier: Programming Language :: Python :: 3.11
Classifier: Programming Language :: Python :: 3.12
Classifier: Programming Language :: Python :: 3.13
Requires-Python: >=3.10
License-File: LICENSE
Requires-Dist: boto3>=1.17.98
Requires-Dist: click>=8.0
Requires-Dist: sentry-sdk<3,>=0.10.2
Requires-Dist: requests>=2.27.1
Requires-Dist: urllib3<3,>=2.5.0
Requires-Dist: unidecode>=1.0.23
Requires-Dist: filelock<4,>=3.0.12
Requires-Dist: pydantic>=2.10.6
Requires-Dist: orjson>=3.10.16
Provides-Extra: all
Requires-Dist: altair==5.5.0; extra == "all"
Requires-Dist: numpy<3,>=1.21.6; extra == "all"
Requires-Dist: openpyxl; extra == "all"
Requires-Dist: pandas>=1.0.3; extra == "all"
Requires-Dist: scikit-bio==0.7.1.post1; extra == "all"
Requires-Dist: scikit-learn>=0.19.0; extra == "all"
Requires-Dist: scikit-posthocs; extra == "all"
Requires-Dist: scipy>=1.11.0; extra == "all"
Provides-Extra: reports
Requires-Dist: altair==5.5.0; extra == "reports"
Requires-Dist: numpy<3,>=1.21.6; extra == "reports"
Requires-Dist: openpyxl; extra == "reports"
Requires-Dist: pandas>=1.0.3; extra == "reports"
Requires-Dist: scikit-bio==0.7.1.post1; extra == "reports"
Requires-Dist: scikit-learn>=0.19.0; extra == "reports"
Requires-Dist: scikit-posthocs; extra == "reports"
Requires-Dist: scipy>=1.11.0; extra == "reports"
Requires-Dist: notebook==6.5.7; extra == "reports"
Requires-Dist: nbconvert>=6.4.3; extra == "reports"
Requires-Dist: WeasyPrint==63.0; extra == "reports"
Requires-Dist: vl-convert-python>=1.6.0; extra == "reports"
Dynamic: license-file
